{"/enable_cc.php": {"27": 1, "28": -1, "29": -2, "30": 1, "31": 1, "32": 1, "33": -2, "34": 1, "36": 1, "37": 1, "39": 1, "40": 1, "43": 1, "45": -1, "46": -1, "47": -1, "49": -1, "50": -1, "51": -1, "52": -1, "55": -1, "57": 1, "62": 1, "63": -1, "64": -1, "66": -1, "69": 1, "70": 1}, "/app/admin/dbconnection.php": {"3": 1, "4": -1, "5": -1, "6": -1, "8": -1, "9": -1, "10": -1, "12": -1, "13": -1, "14": -1, "16": 1, "17": 1, "18": 1, "19": 1, "20": 1, "21": 1, "22": 1, "23": 1, "24": 1, "26": 1, "27": -1, "28": -1, "29": -1, "30": -1, "31": -1, "33": 1, "34": 1, "35": 1, "36": 1, "38": 1, "39": 1}, "/app/admin/index.php": {"3": 1, "4": 1, "5": 1, "6": 1, "8": 1, "9": 1, "10": 1, "12": 1, "13": 1, "14": 1, "16": 1, "17": 1, "18": 1, "19": 1, "20": 1, "21": 1, "22": 1, "23": 1, "24": 1, "25": 1, "26": 1, "27": 1, "28": 1, "29": 1, "30": 1, "31": 1, "32": 1, "33": 1, "34": 1, "35": 1, "36": 1, "37": 1, "38": 1, "39": 1, "40": 1, "41": 1, "43": -1, "44": -1, "45": -1, "46": -1, "47": -1, "48": -1, "49": -1, "50": -1, "52": -2, "53": -2, "54": -2, "55": -2, "57": 1, "58": 1, "59": 1, "60": 1, "62": 1, "89": 1, "90": 1, "91": 1, "113": 1}}